mda_tui/__init__.py
mda_tui/__main__.py
mda_tui/_version.py
mda_tui/mda-tui.tcss
mda_tui/validators.py
mda_tui/widgets/__init__.py
mda_tui/widgets/file_dialogues.py
mda_tui/widgets/file_selectors.py
mda_tui/widgets/run.py
mda_tui/widgets/transformations.py
mda_tui-0.4.0.dist-info/licenses/AUTHORS.md
mda_tui-0.4.0.dist-info/licenses/LICENSE
mda_tui-0.4.0.dist-info/METADATA
mda_tui-0.4.0.dist-info/WHEEL
mda_tui-0.4.0.dist-info/entry_points.txt
mda_tui-0.4.0.dist-info/top_level.txt
mda_tui-0.4.0.dist-info/RECORD
