Metadata-Version: 2.4
Name: mda-tui
Version: 0.4.0
Summary: A textual user interface (TUI) for MDAnalysis
Author-email: Paul Smith <paul.j.smith@ucl.ac.uk>
Maintainer-email: Paul Smith <paul.j.smith@ucl.ac.uk>
License:                     GNU GENERAL PUBLIC LICENSE
Project-URL: source, https://github.com/p-j-smith/mda-tui
Project-URL: homepage, https://p-j-smith.github.io/mda-tui/
Project-URL: bugtracker, https://github.com/p-j-smith/mda-tui/issues
Project-URL: usersupport, https://github.com/p-j-smith/mda-tui/discussions
Project-URL: documentation, https://p-j-smith.github.io/mda-tui/
Keywords: molecular simulations,textual user interface
Requires-Python: >=3.11
License-File: LICENSE
License-File: AUTHORS.md
Requires-Dist: MDAnalysis>=2.10.0
Requires-Dist: textual
Requires-Dist: textual-fspicker
Dynamic: license-file
